graphql_core_promise/__init__.py
graphql_core_promise/py.typed
graphql_core_promise/execute/__init__.py
graphql_core_promise/execute/promise.py
graphql_core_promise_inofficial-3.3.1.dist-info/LICENSE.md
graphql_core_promise_inofficial-3.3.1.dist-info/METADATA
graphql_core_promise_inofficial-3.3.1.dist-info/WHEEL
graphql_core_promise_inofficial-3.3.1.dist-info/top_level.txt
graphql_core_promise_inofficial-3.3.1.dist-info/RECORD
