Metadata-Version: 2.1
Name: graphql-core-promise-inofficial
Version: 3.3.1
Summary: Inofficial fork of graphql-core-promise with a bugfix
Author-email: Samuel Cormier-Iijima <sam@fellow.co>, Shen Li <dustet@gmail.com>
License: BSD-3-Clause
Requires-Python: >=3.10
License-File: LICENSE.md
Requires-Dist: graphql-core>=3.2
Requires-Dist: promise>=2.3
Provides-Extra: dev
Requires-Dist: mypy~=1.9; extra == "dev"
Requires-Dist: pytest~=8.2; extra == "dev"
Requires-Dist: pytest-benchmark~=4.0; extra == "dev"
Requires-Dist: ruff~=0.4; extra == "dev"
